{
  "intro": "#3b82f6",
  "meta": "#8b5cf6",
  "javascript": "#f59e0b",
  "css": "#06b6d4",
  "html": "#ef4444",
  "eleventy": "#10b981",
  "tailwind": "#06b6d4",
  "tutorial": "#f97316",
  "guide": "#84cc16",
  "tips": "#eab308",
  "review": "#6366f1",
  "opinion": "#ec4899",
  "personal": "#14b8a6",
  "tech": "#6b7280",
  "web": "#3b82f6",
  "design": "#8b5cf6",
  "accessibility": "#10b981",
  "performance": "#f59e0b",
  "seo": "#ef4444",
  "indieweb": "#06b6d4",
  "projects": "#0ea5e9",
  "productivity": "#22c55e",
  "weekend": "#f43f5e",
  "markdown": "#64748b",
  "reference": "#0891b2",
  "collaboration": "#a855f7",
  "branding": "#f59e0b",
  "announcement": "#dc2626",
  "announcements": "#dc2626",
  "testing": "#16a34a",
  "jamstack": "#fb923c",
  "retro": "#f472b6",
  "privacy": "#475569",
  "blogging": "#2563eb",
  "thoughts": "#94a3b8",
  "troubleshooting": "#f97316",
  "berry-house": "#ef4444",
  "engineering": "#6366f1"
}
